{
  "campaign_id": null,
  "claim_boundary": {
    "claim_authority": false,
    "live_ready": false,
    "runtime_authority": false,
    "runtime_probe_completed": false
  },
  "conditional_profiles": {
    "cost_execution_profile": {
      "applies": true,
      "fields": {
        "commission_assumption": "broker_native",
        "execution_source": "mt5_strategy_tester",
        "lot": "0.0100",
        "slippage_source": "mt5_strategy_tester",
        "spread_source": "mt5_strategy_tester",
        "starting_balance_usd": 500.0
      }
    },
    "direction_profile": {
      "applies": true,
      "fields": {
        "closed_deal_count": 4527,
        "long_entry_count": 2295,
        "short_entry_count": 2232
      }
    },
    "runtime_reproducibility_profile": {
      "applies": true,
      "fields": {
        "ea_mode": "schedule_replay_for_logic_parity",
        "known_runtime_blockers": [],
        "mt5_tester_status": "completed",
        "runtime_data_availability_status": "tester_output_present"
      }
    },
    "stability_profile": {
      "applies": true,
      "fields": {
        "entry_count_by_fold": {
          "rw_001": 491,
          "rw_002": 517,
          "rw_003": 513,
          "rw_004": 500,
          "rw_005": 486,
          "rw_006": 518,
          "rw_007": 517,
          "rw_008": 493,
          "rw_009": 492
        },
        "profit_count": 4527,
        "trade_count_total": 4527
      }
    },
    "synthesis_schedule_replay_profile": {
      "applies": true,
      "fields": {
        "logic_boundary": "proxy_selected_post_c0030_negative_memory_synthesis_schedule_replayed_in_mt5_closed_bar_mode",
        "model_selected": false,
        "native_mql_training_claim": false,
        "runtime_portability_claim": false,
        "schedule_artifact_path": "campaigns/SC0006_post_c0030_negative_memory_synthesis/runs/SR0001/artifacts/sc0006_sr0001_schedule.csv",
        "schedule_rows": 4527,
        "source_proxy_trade_artifact": "campaigns/SC0006_post_c0030_negative_memory_synthesis/runs/SR0001/artifacts/sc0006_sr0001_proxy_trades.csv"
      }
    },
    "trade_excursion_profile": {
      "applies": false,
      "fields": {}
    }
  },
  "created_at_utc": "2026-07-05T08:03:29Z",
  "deferred_with_reason": [
    {
      "blocking_condition": "candidate quality must be established before materialization work freezes export requirements",
      "claim_boundary": {
        "claim_authority": false,
        "onnx_ready": false,
        "runtime_authority": false
      },
      "field": "native_mql_post_c0030_negative_memory_synthesis_logic",
      "reason": "SC0006 SR0001 replays the proxy schedule in MT5; native model or ONNX materialization is not claimed",
      "requirement_class": "deferred_with_reason",
      "revisit_when": "after fold-isolated MT5 tick evidence supports candidate quality"
    }
  ],
  "missing_required_kpi_fields": [],
  "mt5_date_end": "2026-04-30",
  "mt5_date_start": "2024-02-01",
  "mt5_execution_mode": "logic_parity_closed_bar_exit",
  "mt5_known_blockers": [],
  "mt5_kpi_family": "mt5_logic_parity",
  "mt5_output_scope": null,
  "mt5_probe_id": "MT5-SC0006-SR0001",
  "mt5_probe_status": "completed",
  "mt5_report_hashes": [
    "4ee558dcd3b5bf30ed1f16ff4956cb75e1e35ddc41d472c06b06ea4209038fb6",
    "20b53ac9a72f4f077a8364eebdcf324f760796cae565ab659787df06ee3cb798",
    "b7997240c51c0fe802701f29010e7e31432f31f0987aa13031254185bf335421",
    "0185849b2f265c703a3401de56530d69425a6e81437637dccc0bbb3fdcbb4397"
  ],
  "mt5_report_paths": [
    "C:/Users/awdse/AppData/Roaming/MetaQuotes/Terminal/Common/Files/AxiomRift/SC0006/SR0001/logic_parity/mt5_status.csv",
    "C:/Users/awdse/AppData/Roaming/MetaQuotes/Terminal/Common/Files/AxiomRift/SC0006/SR0001/logic_parity/mt5_events.csv",
    "C:/Users/awdse/AppData/Roaming/MetaQuotes/Terminal/Common/Files/AxiomRift/SC0006/SR0001/logic_parity/mt5_deals.csv",
    "campaigns/SC0006_post_c0030_negative_memory_synthesis/runs/SR0001/artifacts/sc0006_sr0001_schedule.csv"
  ],
  "mt5_status_fields": {
    "balance": "220.38",
    "campaign_id": "SC0006",
    "created_at": "2026.04.30 23:59:59",
    "currency": "USD",
    "detail": "SR0001 MT5 schedule replay completed",
    "entries": "4527",
    "equity": "220.38",
    "exit_evaluation": "closed_bar_ohlc",
    "exits": "4527",
    "leverage": "100",
    "logical_entry_price_basis": "schedule_entry_bar_open",
    "lot": "0.0100",
    "magic": "950001",
    "max_hold_bars": "10",
    "output_mode": "logic_parity",
    "output_scope": "",
    "period_seconds": "300",
    "response_mode": "post_c0030_negative_memory_synthesis_schedule_replay",
    "run_id": "SR0001",
    "schedule_path": "AxiomRift\\SC0006\\SR0001\\schedule\\sc0006_sr0001_schedule.csv",
    "schedule_rows": "4527",
    "signals": "4527",
    "skips": "0",
    "status": "completed",
    "symbol": "US100"
  },
  "mt5_symbol": "US100",
  "mt5_terminal_identity": "C:/Users/awdse/AppData/Roaming/MetaQuotes/Terminal/D0E8209F77C8CF37AD8BF550E51FF075",
  "mt5_tester_model": "open_prices_model_2",
  "mt5_tester_to_date": "2026-05-01",
  "mt5_timeframe": "M5",
  "required_kpis": {
    "mt5_execution_mode": "logic_parity_closed_bar_exit",
    "mt5_exit_evaluation": "closed_bar_ohlc",
    "mt5_expectancy_per_entry": -0.061767,
    "mt5_max_drawdown_percent": 55.978,
    "mt5_net_pnl": -279.62,
    "mt5_output_mode": "logic_parity",
    "mt5_profit_factor": 0.53791,
    "mt5_trade_count": 4527,
    "mt5_win_rate": 0.33245
  },
  "requirement_policy": "required_and_conditional_required_with_deferred_reason",
  "run_id": "SR0001",
  "runtime_config_path": "configs/runtime.yaml",
  "runtime_config_sha256": "7549a904443d4d0a926e55579437391c58ee82facd3f364eef58a0ee9f5ddfc7",
  "runtime_config_snapshot": {
    "claim_boundary": {
      "active_runtime_config_complete": true,
      "live_ready": false,
      "runtime_authority": false
    },
    "execution": {
      "cost_behavior": "broker_native_until_contract_says_otherwise",
      "default_lot": 0.01,
      "position_management": "tick_runtime",
      "signal_timing": "closed_m5_bar"
    },
    "mt5": {
      "broker_server": "FPMarketsSC-Live",
      "deposit": 500,
      "deposit_currency": "USD",
      "execution_mode": 0,
      "leverage": 100,
      "logic_parity_model": 2,
      "metaeditor_exe": "C:/Program Files/MetaTrader 5/MetaEditor64.exe",
      "symbol": "US100",
      "terminal_data_dir": "C:/Users/awdse/AppData/Roaming/MetaQuotes/Terminal/D0E8209F77C8CF37AD8BF550E51FF075",
      "terminal_exe": "C:/Program Files/MetaTrader 5/terminal64.exe",
      "terminal_mode": "headless",
      "tester_model": "real_ticks",
      "tick_execution_model": 4,
      "timeframe": "M5"
    },
    "schema": "axiom_rift_runtime_config_v1",
    "status": "active_runtime_baseline"
  },
  "schema": "axiom_rift_mt5_logic_parity_kpi_v1",
  "synthesis_id_when_applicable": "SC0006",
  "template": false,
  "work_unit_id": "SC0006"
}
